checkreg/__init__.py
checkreg/aes.py
checkreg/dangdang.py
checkreg_zhongpu-0.0.2.dist-info/LICENSE
checkreg_zhongpu-0.0.2.dist-info/METADATA
checkreg_zhongpu-0.0.2.dist-info/WHEEL
checkreg_zhongpu-0.0.2.dist-info/top_level.txt
checkreg_zhongpu-0.0.2.dist-info/RECORD
