Metadata-Version: 2.1
Name: checkreg-zhongpu
Version: 0.0.2
Summary: A package to check whether it has been registered
Home-page: https://github.com/ChenZhongPu/checkReg
Author: Zhongpu Chen
Author-email: chenloveit@gmail.com
Project-URL: Bug Tracker, https://github.com/ChenZhongPu/checkReg/issues
Classifier: Programming Language :: Python :: 3
Classifier: License :: OSI Approved :: MIT License
Classifier: Operating System :: OS Independent
Requires-Python: >=3.6
License-File: LICENSE
Requires-Dist: pycryptodome
Requires-Dist: requests
